bpydevutil/__init__.py
bpydevutil/functions/common_funcs.py
bpydevutil/functions/install_funcs.py
bpydevutil/functions/pack_funcs.py
bpydevutil/functions/symlink_funcs.py
bpydevutil/main.py
bpy_dev_utils-0.1.0.dist-info/entry_points.txt
bpy_dev_utils-0.1.0.dist-info/WHEEL
bpy_dev_utils-0.1.0.dist-info/METADATA
bpy_dev_utils-0.1.0.dist-info/RECORD
