Metadata-Version: 2.1
Name: bpy-dev-utils
Version: 0.1.0
Summary: This is a personal collection of simple CLI utilities that I made to help my development of Blender addons.
Author: Matt Ashpole
Author-email: m.d.ashpole@gmail.com
Requires-Python: >=3.9,<4.0
Classifier: Programming Language :: Python :: 3
Classifier: Programming Language :: Python :: 3.9
Classifier: Programming Language :: Python :: 3.10
Requires-Dist: rich (>=12.5.1,<13.0.0)
Requires-Dist: typer (>=0.7.0,<0.8.0)
